Metadata-Version: 2.1
Name: python-libthai
Version: 0.1.4
Summary: Python - libthai binding library.
Home-page: https://github.com/teerasit-ang
Author: Teerasit Angkhaprsertkul
Author-email: teerasit.ang@gmail.com
License: GNU
Keywords: thai language linguistics segmentation
Platform: UNKNOWN
Classifier: Development Status :: 5 - Production/Stable
Classifier: Intended Audience :: Developers
Classifier: License :: OSI Approved :: GNU Lesser General Public License v3 (LGPLv3)
Classifier: Topic :: Software Development :: Libraries :: Python Modules
Classifier: Topic :: Text Processing :: Linguistic
